smartrent/__init__.py
smartrent/api.py
smartrent/device.py
smartrent/lock.py
smartrent/sensor.py
smartrent/switch.py
smartrent/thermostat.py
smartrent/utils.py
smartrent_py-0.5.2.dist-info/LICENSE.md
smartrent_py-0.5.2.dist-info/WHEEL
smartrent_py-0.5.2.dist-info/METADATA
smartrent_py-0.5.2.dist-info/RECORD
