Metadata-Version: 2.1
Name: smartrent-py
Version: 0.5.2
Summary: Unofficial Python API for SmartRent devices
Home-page: https://github.com/zacherythomas/smartrent-py
License: MIT
Author: Zachery Thomas
Author-email: zacherythomas12@gmail.com
Requires-Python: >=3.6.1,<4.0.0
Classifier: License :: OSI Approved :: MIT License
Classifier: Programming Language :: Python :: 3
Classifier: Programming Language :: Python :: 3.10
Classifier: Programming Language :: Python :: 3.7
Classifier: Programming Language :: Python :: 3.8
Classifier: Programming Language :: Python :: 3.9
Requires-Dist: aiohttp (>=3.8.4,<4.0.0)
Requires-Dist: websockets (>=15.0.1,<16.0.0)
Project-URL: Documentation, https://smartrentpy.readthedocs.io
Project-URL: Repository, https://github.com/zacherythomas/smartrent-py
